{
  "cli_version": "0.8.42",
  "checkpoint_id": "6df2eebd2e44",
  "session_id": "019f065f-8537-77a3-9e46-4075c1fb8377",
  "strategy": "import",
  "created_at": "2026-06-27T00:01:26.947Z",
  "checkpoints_count": 1,
  "files_touched": null,
  "agent": "Codex",
  "model": "",
  "checkpoint_transcript_start": 60,
  "transcript_lines_at_start": 60,
  "compact_transcript_start": 12,
  "token_usage": {
    "input_tokens": 16668,
    "cache_creation_tokens": 0,
    "cache_read_tokens": 7040,
    "output_tokens": 49,
    "api_call_count": 1
  },
  "kind": "imported"
}
